crankshaft/__init__.py
crankshaft/modules/api.bolt
crankshaft/modules/config.bolt
crankshaft/modules/cwd.bolt
crankshaft/modules/event_handler/class_support.bolt
crankshaft/modules/event_handler/event_definition.bolt
crankshaft/modules/event_handler/listeners.bolt
crankshaft/modules/event_handler/optimizer.bolt
crankshaft/modules/event_handler/registry.bolt
crankshaft/modules/events.bolt
crankshaft/modules/flag_handler.bolt
crankshaft/modules/flags.bolt
crankshaft/modules/utils.bolt
crankshaft/py.typed
crankshaft-1.0.0.dist-info/LICENSE
crankshaft-1.0.0.dist-info/METADATA
crankshaft-1.0.0.dist-info/WHEEL
crankshaft-1.0.0.dist-info/RECORD
