Metadata-Version: 2.1
Name: crankshaft
Version: 1.0.0
Summary: Bolt datapack flow control library.
Home-page: https://github.com/reapermc/crankshaft
License: MIT
Keywords: beet,mecha,bolt,python,minecraft,datapack,minecraft-commands,mcfunction,crankshaft,library,reapermc,flow-control,event,event-handler
Author: ArcticYeti
Author-email: arcticyeti1@gmail.com
Requires-Python: >=3.12,<4.0
Classifier: License :: OSI Approved :: MIT License
Classifier: Programming Language :: Python :: 3
Classifier: Programming Language :: Python :: 3.12
Requires-Dist: beet (>=0.84.0)
Requires-Dist: bolt (>=0.31.0)
Requires-Dist: lightning-rod (>=0.2.0)
Requires-Dist: mecha (>=0.67.0)
Requires-Dist: wicked-expressions (>=0.6.0)
